{
    "name": "Badia Polesine",
    "people": [
        {
            "page": "Mattia Signorini",
            "pageView": 9147
        },
        {
            "page": "Eugenio Balzan",
            "pageView": 8999
        },
        {
            "page": "Gregorio Lazzarini",
            "pageView": 8271
        },
        {
            "page": "Armando Rigobello",
            "pageView": 8153
        },
        {
            "page": "Maurizio Marchetto",
            "pageView": 6392
        },
        {
            "page": "Valentino Degani",
            "pageView": 6238
        },
        {
            "page": "Girolamo Brusoni",
            "pageView": 6111
        },
        {
            "page": "Nadir Tedeschi",
            "pageView": 5622
        },
        {
            "page": "Vic Nocera",
            "pageView": 4616
        },
        {
            "page": "Gherardo Ghirardini",
            "pageView": 3410
        },
        {
            "page": "Amedeo Bianchi",
            "pageView": 3186
        },
        {
            "page": "Luciano Nezzo",
            "pageView": 2669
        },
        {
            "page": "Giuseppe De Marchi",
            "pageView": 2069
        },
        {
            "page": "Luigi Balzan",
            "pageView": 1841
        },
        {
            "page": "Jotti da Badia Polesine",
            "pageView": 1472
        }
    ]
}