{
    "name": "Montepulciano",
    "people": [
        {
            "page": "Andrea Pazienza",
            "pageView": 508757
        },
        {
            "page": "Agnolo Poliziano",
            "pageView": 144336
        },
        {
            "page": "Francesco Bianconi",
            "pageView": 134970
        },
        {
            "page": "Roberto Bellarmino",
            "pageView": 130160
        },
        {
            "page": "Giovanni Della Casa",
            "pageView": 92346
        },
        {
            "page": "Elémire Zolla",
            "pageView": 74697
        },
        {
            "page": "Rodolfo Cetoloni",
            "pageView": 11074
        },
        {
            "page": "Stefano Manetti",
            "pageView": 9759
        },
        {
            "page": "Cino Cinelli",
            "pageView": 9129
        },
        {
            "page": "Franco Ceccuzzi",
            "pageView": 8094
        },
        {
            "page": "Roberto de Nobili",
            "pageView": 6489
        },
        {
            "page": "Marco Coltellini",
            "pageView": 6259
        },
        {
            "page": "Paolo Parisi",
            "pageView": 5785
        },
        {
            "page": "Mario Guidotti",
            "pageView": 4367
        },
        {
            "page": "Dino Trabalzini",
            "pageView": 4161
        },
        {
            "page": "Giovanni Antonio Pandolfi Mealli",
            "pageView": 4017
        },
        {
            "page": "Francesco Maria Tarugi",
            "pageView": 3931
        },
        {
            "page": "Ugo Mioni",
            "pageView": 3818
        },
        {
            "page": "Roberto Ubaldini",
            "pageView": 3611
        },
        {
            "page": "Giovanni Battista Fioretti",
            "pageView": 3127
        },
        {
            "page": "Mario Specchio",
            "pageView": 3064
        },
        {
            "page": "Bartolomeo Massei",
            "pageView": 2970
        },
        {
            "page": "Pietro Bucelli",
            "pageView": 2849
        },
        {
            "page": "Cesare Nerazzini",
            "pageView": 2676
        },
        {
            "page": "Pasquino da Montepulciano",
            "pageView": 2603
        },
        {
            "page": "Bartolomeo Aragazzi",
            "pageView": 2582
        },
        {
            "page": "Roberto de' Nobili",
            "pageView": 2552
        },
        {
            "page": "Sallustio Tarugi",
            "pageView": 2448
        },
        {
            "page": "Benincasa (beato)",
            "pageView": 2320
        },
        {
            "page": "Giovanni Boscoli",
            "pageView": 2163
        },
        {
            "page": "Lidio Bozzini",
            "pageView": 2102
        },
        {
            "page": "Cesare Sabelli",
            "pageView": 1905
        },
        {
            "page": "Bartolomeo Pucci",
            "pageView": 1607
        },
        {
            "page": "Paolo Massei",
            "pageView": 1462
        },
        {
            "page": "Vincenzo Cozzani",
            "pageView": 1421
        },
        {
            "page": "Ilio Calabresi",
            "pageView": 1416
        },
        {
            "page": "Gabriello Puliti",
            "pageView": 1311
        },
        {
            "page": "Francesco Crociani",
            "pageView": 1287
        },
        {
            "page": "Contuccio Contucci",
            "pageView": 1256
        },
        {
            "page": "Agnese di Montepulciano",
            "pageView": 1064
        },
        {
            "page": "Giovanni Nardi (medico)",
            "pageView": 1037
        },
        {
            "page": "Zelindo Ciro Boddi",
            "pageView": 903
        },
        {
            "page": "Mario Mencatelli",
            "pageView": 268
        },
        {
            "page": "Bartolomeo Pucci-Franceschi",
            "pageView": 47
        }
    ]
}