{
    "name": "Vigo di Cadore",
    "people": [
        {
            "page": "Adeodato Piazza",
            "pageView": 7,
            "total": 8377
        },
        {
            "page": "Tomaso Da Rin",
            "pageView": 2,
            "total": 3505
        },
        {
            "page": "Antonio Ronzon",
            "pageView": 2,
            "total": 2239
        },
        {
            "page": "Ainardo di Vigo",
            "pageView": 1,
            "total": 1293
        }
    ]
}