{
    "name": "Barga",
    "people": [
        {
            "page": "Federico Mattiello",
            "pageView": 112,
            "total": 246515
        },
        {
            "page": "Gualtiero Jacopetti",
            "pageView": 26,
            "total": 43661
        },
        {
            "page": "Andrea Marcucci",
            "pageView": 25,
            "total": 85783
        },
        {
            "page": "Nadia Centoni",
            "pageView": 19,
            "total": 44685
        },
        {
            "page": "Lorenzo Baldisseri",
            "pageView": 16,
            "total": 25662
        },
        {
            "page": "Marialina Marcucci",
            "pageView": 11,
            "total": 21688
        },
        {
            "page": "Roberto Bacci",
            "pageView": 10,
            "total": 15190
        },
        {
            "page": "Antonio Mordini",
            "pageView": 5,
            "total": 9015
        },
        {
            "page": "Emanuele Venturelli",
            "pageView": 3,
            "total": 4063
        },
        {
            "page": "Bruno Cordati",
            "pageView": 2,
            "total": 1415
        },
        {
            "page": "Baccio Ciarpi",
            "pageView": 2,
            "total": 3019
        },
        {
            "page": "Paolo Riani",
            "pageView": 2,
            "total": 3109
        },
        {
            "page": "Ferruccio Giannini",
            "pageView": 2,
            "total": 2709
        },
        {
            "page": "Cesare Biondi",
            "pageView": 2,
            "total": 2026
        },
        {
            "page": "Pietro degli Angeli",
            "pageView": 2,
            "total": 3220
        },
        {
            "page": "Amos Paoli",
            "pageView": 2,
            "total": 2549
        },
        {
            "page": "Alfredo Bonaccorsi",
            "pageView": 1,
            "total": 1496
        },
        {
            "page": "Giacomo Maremmani",
            "pageView": 0,
            "total": 548
        }
    ]
}