{
    "name": "Calvizzano",
    "people": [
        {
            "page": "Giulio Di Donato",
            "pageView": 7,
            "total": 10946
        },
        {
            "page": "Giuseppe Mirabelli",
            "pageView": 3,
            "total": 4053
        },
        {
            "page": "Raffaele Chianese",
            "pageView": 2,
            "total": 3875
        },
        {
            "page": "Domenico Biondi",
            "pageView": 1,
            "total": 1551
        }
    ]
}