{
    "name": "Crespellano",
    "people": [
        {
            "page": "Gabriella Degli Esposti",
            "pageView": 6,
            "total": 14150
        },
        {
            "page": "Tommaso Casini",
            "pageView": 3,
            "total": 4336
        },
        {
            "page": "Luigi Ferri (giurista)",
            "pageView": 2,
            "total": 3121
        },
        {
            "page": "Ugo Gheduzzi",
            "pageView": 2,
            "total": 2942
        },
        {
            "page": "Faustino Malaguti",
            "pageView": 1,
            "total": 1628
        }
    ]
}