{
    "name": "Mammola",
    "people": [
        {
            "page": "Maria Carmela Lanzetta",
            "pageView": 16,
            "total": 30116
        },
        {
            "page": "Nik Spatari",
            "pageView": 12,
            "total": 29264
        },
        {
            "page": "Nick Mancuso",
            "pageView": 8,
            "total": 17565
        },
        {
            "page": "Pino Callà",
            "pageView": 4,
            "total": 7030
        },
        {
            "page": "Apollinare Agresta",
            "pageView": 2,
            "total": 3155
        },
        {
            "page": "Vincenzo Guerrazzi",
            "pageView": 2,
            "total": 3364
        },
        {
            "page": "Vincent Cotroni",
            "pageView": 0,
            "total": 505
        }
    ]
}