{
    "name": "Nocera Inferiore",
    "people": [
        {
            "page": "Coez",
            "pageView": 400.5,
            "total": 976363
        },
        {
            "page": "Mino Raiola",
            "pageView": 281,
            "total": 935271
        },
        {
            "page": "Simone Barone",
            "pageView": 92,
            "total": 186860
        },
        {
            "page": "Gianfranco Miranda",
            "pageView": 92,
            "total": 144045
        },
        {
            "page": "Giuseppe Marrazzo",
            "pageView": 41,
            "total": 86175
        },
        {
            "page": "Jolanda Granato",
            "pageView": 35,
            "total": 54237
        },
        {
            "page": "Giammario Piscitella",
            "pageView": 27,
            "total": 47107
        },
        {
            "page": "Edmondo Cirielli",
            "pageView": 23,
            "total": 42770
        },
        {
            "page": "Raffaele De Martino",
            "pageView": 16,
            "total": 28372
        },
        {
            "page": "Raffaele Gragnaniello",
            "pageView": 11,
            "total": 19027
        },
        {
            "page": "Fabrizio Pasqua",
            "pageView": 10,
            "total": 46401
        },
        {
            "page": "Luca Infante",
            "pageView": 9,
            "total": 16882
        },
        {
            "page": "Francesco Alfano",
            "pageView": 8,
            "total": 13245
        },
        {
            "page": "Michele Tarallo",
            "pageView": 7,
            "total": 11936
        },
        {
            "page": "Isabella Adinolfi",
            "pageView": 6,
            "total": 14716
        },
        {
            "page": "Nando Citarella",
            "pageView": 5,
            "total": 8187
        },
        {
            "page": "Pasquale Villani",
            "pageView": 4,
            "total": 6714
        },
        {
            "page": "Giovanni Amato",
            "pageView": 4,
            "total": 7170
        },
        {
            "page": "Giuseppe Consagno",
            "pageView": 3,
            "total": 5008
        },
        {
            "page": "Ivanoe Lanzara",
            "pageView": 3,
            "total": 4953
        },
        {
            "page": "Antonio Napoletano",
            "pageView": 3,
            "total": 5128
        },
        {
            "page": "Salvatore Sarno",
            "pageView": 3,
            "total": 4522
        },
        {
            "page": "Paolo Ramora",
            "pageView": 3,
            "total": 5559
        },
        {
            "page": "Michele Sellitti",
            "pageView": 2,
            "total": 2030
        },
        {
            "page": "Rachele La Rotonda Compagnone",
            "pageView": 2,
            "total": 2412
        },
        {
            "page": "Olga Elia",
            "pageView": 2,
            "total": 1868
        },
        {
            "page": "Lorenzo Fava",
            "pageView": 2,
            "total": 3050
        },
        {
            "page": "Vincenzo Calenda di Tavani",
            "pageView": 2,
            "total": 3484
        },
        {
            "page": "Dario Galante",
            "pageView": 2,
            "total": 1762
        },
        {
            "page": "Francesco Curci (politico)",
            "pageView": 2,
            "total": 2332
        },
        {
            "page": "Prisco Palumbo",
            "pageView": 2,
            "total": 3988
        },
        {
            "page": "Andrea Calenda di Tavani",
            "pageView": 2,
            "total": 2050
        },
        {
            "page": "Nicola Bruni Grimaldi",
            "pageView": 2,
            "total": 1894
        },
        {
            "page": "Alfredo Pucci",
            "pageView": 2,
            "total": 1932
        },
        {
            "page": "Alfonso Cuomo",
            "pageView": 2,
            "total": 3630
        },
        {
            "page": "Salvatore Pucci",
            "pageView": 2,
            "total": 3365
        },
        {
            "page": "Saverio Costantino Amato",
            "pageView": 2,
            "total": 2504
        },
        {
            "page": "Angelo Serio",
            "pageView": 2,
            "total": 2655
        },
        {
            "page": "Alfonso Orlando",
            "pageView": 2,
            "total": 2569
        },
        {
            "page": "Raffaele Pucci",
            "pageView": 1,
            "total": 1391
        },
        {
            "page": "Aristide Sellitti",
            "pageView": 1,
            "total": 1113
        },
        {
            "page": "Pietro Colella",
            "pageView": 1,
            "total": 1718
        },
        {
            "page": "Vincenzo Comitini",
            "pageView": 1,
            "total": 1094
        },
        {
            "page": "Guido Cucci",
            "pageView": 1,
            "total": 1320
        }
    ]
}