{
    "name": "Oristano",
    "people": [
        {
            "page": "Tiberio Murgia",
            "pageView": 81,
            "total": 167716
        },
        {
            "page": "Nicola Farron",
            "pageView": 64,
            "total": 112388
        },
        {
            "page": "Benito Urgu",
            "pageView": 55,
            "total": 99655
        },
        {
            "page": "Alessia Orro",
            "pageView": 35,
            "total": 87506
        },
        {
            "page": "Cristian Cocco",
            "pageView": 15,
            "total": 34949
        },
        {
            "page": "Mariano IV d'Arborea",
            "pageView": 13,
            "total": 20418
        },
        {
            "page": "Antonino Arconte",
            "pageView": 12,
            "total": 19752
        },
        {
            "page": "Leonardo Alagon",
            "pageView": 8,
            "total": 12872
        },
        {
            "page": "Franco Ligas",
            "pageView": 7,
            "total": 13700
        },
        {
            "page": "Federica Daga",
            "pageView": 6,
            "total": 11099
        },
        {
            "page": "Paolo Piras",
            "pageView": 5,
            "total": 8427
        },
        {
            "page": "Sergio Pintor",
            "pageView": 5,
            "total": 7495
        },
        {
            "page": "Andrea Lutzu",
            "pageView": 5,
            "total": 2887
        },
        {
            "page": "Umberto Erriu",
            "pageView": 5,
            "total": 7655
        },
        {
            "page": "Peter Marcias",
            "pageView": 4,
            "total": 8336
        },
        {
            "page": "Lucio Abis",
            "pageView": 4,
            "total": 5966
        },
        {
            "page": "Stefano Oppo",
            "pageView": 3,
            "total": 6749
        },
        {
            "page": "Roberto Ennas",
            "pageView": 3,
            "total": 2573
        },
        {
            "page": "Valentina Uccheddu",
            "pageView": 3,
            "total": 4706
        },
        {
            "page": "Antonio Garau",
            "pageView": 3,
            "total": 4398
        },
        {
            "page": "Alessandro Ghinami",
            "pageView": 3,
            "total": 6318
        },
        {
            "page": "Lucia Scanu",
            "pageView": 3,
            "total": 1537
        },
        {
            "page": "Alfredo Corrias",
            "pageView": 3,
            "total": 3767
        },
        {
            "page": "Flavio Busonera",
            "pageView": 3,
            "total": 5906
        },
        {
            "page": "Mariano II di Arborea",
            "pageView": 3,
            "total": 5102
        },
        {
            "page": "Raimondo Carta Raspi",
            "pageView": 3,
            "total": 4081
        },
        {
            "page": "Franco Casu",
            "pageView": 3,
            "total": 4643
        },
        {
            "page": "Ignazio Manunza",
            "pageView": 2,
            "total": 2214
        },
        {
            "page": "Ugone I di Arborea",
            "pageView": 2,
            "total": 3784
        },
        {
            "page": "Francesco Fancello",
            "pageView": 2,
            "total": 3644
        },
        {
            "page": "Anna Rita Angotzi",
            "pageView": 2,
            "total": 3407
        },
        {
            "page": "Pietro I di Arborea",
            "pageView": 2,
            "total": 1827
        },
        {
            "page": "Mario Pinna",
            "pageView": 2,
            "total": 3360
        },
        {
            "page": "Milko Campus",
            "pageView": 2,
            "total": 2306
        },
        {
            "page": "Stefano Loddo",
            "pageView": 2,
            "total": 1757
        },
        {
            "page": "Massimo Piras",
            "pageView": 2,
            "total": 2893
        },
        {
            "page": "Abele Saba",
            "pageView": 1,
            "total": 1146
        },
        {
            "page": "Angelina Cabras",
            "pageView": 1,
            "total": 1715
        },
        {
            "page": "Salvatore Campus",
            "pageView": 1,
            "total": 1255
        },
        {
            "page": "Francesco Deias",
            "pageView": 1,
            "total": 1467
        },
        {
            "page": "Savina Dolores Massa",
            "pageView": 0,
            "total": 997
        },
        {
            "page": "Francesco Sonis",
            "pageView": 0,
            "total": 911
        }
    ]
}