{
    "name": "Randazzo",
    "people": [
        {
            "page": "Domenico Spadafora",
            "pageView": 3,
            "total": 5772
        },
        {
            "page": "Casimiro Bonfiglio",
            "pageView": 2,
            "total": 2080
        },
        {
            "page": "Erasmo Marotta",
            "pageView": 2,
            "total": 2170
        },
        {
            "page": "Nicola Petrina",
            "pageView": 2,
            "total": 1916
        },
        {
            "page": "Andrea Capparelli",
            "pageView": 1,
            "total": 1674
        },
        {
            "page": "Francesco Paolo Finocchiaro",
            "pageView": 1,
            "total": 796
        },
        {
            "page": "Antonino da Randazzo",
            "pageView": 1,
            "total": 1567
        },
        {
            "page": "Maurizio Damiano",
            "pageView": 0,
            "total": 1036
        }
    ]
}