{
    "name": "San Benedetto Po",
    "people": [
        {
            "page": "Kevin Lasagna",
            "pageView": 163,
            "total": 548627
        },
        {
            "page": "Ernesto Ruffini",
            "pageView": 22,
            "total": 37146
        },
        {
            "page": "Enrico Ferri (criminologo)",
            "pageView": 19,
            "total": 27851
        },
        {
            "page": "Gino Mescoli",
            "pageView": 5,
            "total": 8569
        },
        {
            "page": "Umberto Bellintani",
            "pageView": 3,
            "total": 5345
        },
        {
            "page": "Cesare Cambi",
            "pageView": 1,
            "total": 1380
        },
        {
            "page": "Ermanno Pittigliani",
            "pageView": 1,
            "total": 1373
        },
        {
            "page": "Biagio Virgili",
            "pageView": 1,
            "total": 1320
        }
    ]
}