{
    "name": "Scansano",
    "people": [
        {
            "page": "Dina Luce",
            "pageView": 6,
            "total": 9506
        },
        {
            "page": "Franco Franchi (politico)",
            "pageView": 3,
            "total": 3854
        },
        {
            "page": "Enrico Parri",
            "pageView": 2,
            "total": 1750
        },
        {
            "page": "Virgilio Ducceschi",
            "pageView": 1,
            "total": 1745
        },
        {
            "page": "Giovanni Pizzetti",
            "pageView": 0,
            "total": 527
        },
        {
            "page": "Alessandro Romani (pittore)",
            "pageView": 0,
            "total": 622
        },
        {
            "page": "Domenico Tonarelli",
            "pageView": 0,
            "total": 312
        },
        {
            "page": "Angelo Valle",
            "pageView": 0,
            "total": 318
        }
    ]
}