{
    "name": "Sesto San Giovanni",
    "people": [
        {
            "page": "Sfera Ebbasta",
            "pageView": 1857,
            "total": 2333565
        },
        {
            "page": "Gino Strada",
            "pageView": 181,
            "total": 457609
        },
        {
            "page": "Massimo Carrera",
            "pageView": 104,
            "total": 226474
        },
        {
            "page": "Stefano Guberti",
            "pageView": 61,
            "total": 134975
        },
        {
            "page": "Alessandro Milan",
            "pageView": 45,
            "total": 116462
        },
        {
            "page": "Gianfranco Paglia",
            "pageView": 29,
            "total": 55638
        },
        {
            "page": "Fabio Macellari",
            "pageView": 23,
            "total": 41376
        },
        {
            "page": "Walter Alasia",
            "pageView": 23,
            "total": 45006
        },
        {
            "page": "Teresa Sarti Strada",
            "pageView": 22,
            "total": 64107
        },
        {
            "page": "Ettore Conti",
            "pageView": 19,
            "total": 31627
        },
        {
            "page": "Simone Sini",
            "pageView": 12,
            "total": 21229
        },
        {
            "page": "Giancarlo Danova",
            "pageView": 12,
            "total": 18631
        },
        {
            "page": "Barbara Fusar Poli",
            "pageView": 11,
            "total": 24981
        },
        {
            "page": "Mario Trebbi",
            "pageView": 9,
            "total": 17303
        },
        {
            "page": "Stefano Tessarin",
            "pageView": 9,
            "total": 14267
        },
        {
            "page": "Federico Faruffini",
            "pageView": 9,
            "total": 14595
        },
        {
            "page": "Massimiliano Caniato",
            "pageView": 9,
            "total": 14045
        },
        {
            "page": "Marco Saligari",
            "pageView": 8,
            "total": 55266
        },
        {
            "page": "Enrico Galmozzi",
            "pageView": 8,
            "total": 14957
        },
        {
            "page": "Mario Viganò",
            "pageView": 7,
            "total": 11729
        },
        {
            "page": "Fabio Celoni",
            "pageView": 6,
            "total": 9280
        },
        {
            "page": "Giovanni Bianchi (politico)",
            "pageView": 6,
            "total": 14286
        },
        {
            "page": "Francesco Tabusso",
            "pageView": 5,
            "total": 7549
        },
        {
            "page": "Guido Scarabottolo",
            "pageView": 5,
            "total": 2634
        },
        {
            "page": "Martina Crippa",
            "pageView": 4,
            "total": 9139
        },
        {
            "page": "Angelo Mascheroni (vescovo)",
            "pageView": 4,
            "total": 6848
        },
        {
            "page": "Ettore Adalberto Albertoni",
            "pageView": 4,
            "total": 7947
        },
        {
            "page": "Marco Enrico Ricotti",
            "pageView": 4,
            "total": 2376
        },
        {
            "page": "Anselmo Bislenghi",
            "pageView": 3,
            "total": 4216
        },
        {
            "page": "Paolo Giuliani",
            "pageView": 3,
            "total": 3907
        },
        {
            "page": "Giuseppe Vigoni",
            "pageView": 3,
            "total": 3944
        },
        {
            "page": "Ferdinando Terruzzi",
            "pageView": 3,
            "total": 4562
        },
        {
            "page": "Giovanni Sacchi",
            "pageView": 3,
            "total": 5207
        },
        {
            "page": "Giulio Casiraghi",
            "pageView": 3,
            "total": 4756
        },
        {
            "page": "Carlo Negri (autore televisivo)",
            "pageView": 3,
            "total": 7144
        },
        {
            "page": "Carlo Zecchini",
            "pageView": 3,
            "total": 5654
        },
        {
            "page": "Marco Lorini",
            "pageView": 2,
            "total": 2029
        },
        {
            "page": "Giovanni Drovetti",
            "pageView": 2,
            "total": 2632
        },
        {
            "page": "Raffaello Ducceschi",
            "pageView": 2,
            "total": 3744
        },
        {
            "page": "Francesco Meregalli",
            "pageView": 2,
            "total": 3597
        },
        {
            "page": "Angelo Meroni",
            "pageView": 2,
            "total": 2663
        },
        {
            "page": "Achille Brioschi (calciatore)",
            "pageView": 2,
            "total": 2657
        },
        {
            "page": "Ezio Monti",
            "pageView": 2,
            "total": 3113
        },
        {
            "page": "Giulio Vigoni",
            "pageView": 2,
            "total": 2241
        },
        {
            "page": "Giuseppe Fusi",
            "pageView": 2,
            "total": 2559
        },
        {
            "page": "Biri (paroliera)",
            "pageView": 2,
            "total": 3608
        },
        {
            "page": "Nicolás Cotugno Fanizzi",
            "pageView": 2,
            "total": 2645
        },
        {
            "page": "Nadia Raimondi",
            "pageView": 2,
            "total": 1988
        },
        {
            "page": "Elena Sordelli",
            "pageView": 2,
            "total": 2682
        },
        {
            "page": "Giacomo Rigoni",
            "pageView": 2,
            "total": 2734
        },
        {
            "page": "Aurelio Crippa",
            "pageView": 2,
            "total": 3848
        },
        {
            "page": "Franco Carminati",
            "pageView": 2,
            "total": 2927
        },
        {
            "page": "Felice Lacerra",
            "pageView": 2,
            "total": 941
        },
        {
            "page": "Giosuè Sanvito",
            "pageView": 2,
            "total": 2622
        },
        {
            "page": "Stefano Aigotti",
            "pageView": 2,
            "total": 3280
        },
        {
            "page": "Erminio Teruzzi",
            "pageView": 1,
            "total": 1241
        },
        {
            "page": "Egidio Lorenzi",
            "pageView": 1,
            "total": 1181
        },
        {
            "page": "Gianna Alfieri",
            "pageView": 1,
            "total": 1082
        },
        {
            "page": "Gaetano Gaslini",
            "pageView": 1,
            "total": 1213
        },
        {
            "page": "Costantino Galbiati",
            "pageView": 1,
            "total": 1407
        },
        {
            "page": "Giuseppe Corti (1920)",
            "pageView": 1,
            "total": 1497
        },
        {
            "page": "Eugenio Cestari",
            "pageView": 1,
            "total": 1250
        },
        {
            "page": "Araldo Pirola",
            "pageView": 1,
            "total": 1602
        },
        {
            "page": "Piero Cereda",
            "pageView": 1,
            "total": 1117
        },
        {
            "page": "Giuseppe Casati",
            "pageView": 1,
            "total": 1380
        },
        {
            "page": "Pietro Valenzano",
            "pageView": 1,
            "total": 1544
        },
        {
            "page": "Pietro Bruno Cattaneo",
            "pageView": 0,
            "total": 1384
        },
        {
            "page": "Stefania Calegari",
            "pageView": 0,
            "total": 158
        },
        {
            "page": "Pierangelo Paleari",
            "pageView": 0,
            "total": 547
        },
        {
            "page": "Claudio Sadler",
            "pageView": 0,
            "total": 6386
        }
    ]
}