{
    "name": "Sestri Levante",
    "people": [
        {
            "page": "Carlo Bo",
            "pageView": 56,
            "total": 83988
        },
        {
            "page": "Luigi Lambruschini",
            "pageView": 8,
            "total": 12114
        },
        {
            "page": "Vito Molinari",
            "pageView": 7,
            "total": 15490
        },
        {
            "page": "Bruno Baveni",
            "pageView": 6,
            "total": 10406
        },
        {
            "page": "Giorgio Bo",
            "pageView": 6,
            "total": 9548
        },
        {
            "page": "Guido Stagnaro",
            "pageView": 5,
            "total": 9436
        },
        {
            "page": "Samuele Podestà",
            "pageView": 5,
            "total": 8685
        },
        {
            "page": "Fosco Becattini",
            "pageView": 5,
            "total": 10135
        },
        {
            "page": "Renzo Uzzecchini",
            "pageView": 4,
            "total": 5360
        },
        {
            "page": "Corrado Rollero",
            "pageView": 4,
            "total": 6217
        },
        {
            "page": "Giovanni Descalzo",
            "pageView": 3,
            "total": 4486
        },
        {
            "page": "Eraldo Fico",
            "pageView": 3,
            "total": 4803
        },
        {
            "page": "Neria De Giovanni",
            "pageView": 3,
            "total": 5185
        },
        {
            "page": "Giorgia Gueglio",
            "pageView": 3,
            "total": 4439
        },
        {
            "page": "Rino Di Fraia",
            "pageView": 3,
            "total": 4800
        },
        {
            "page": "Ferdinando Lambruschini",
            "pageView": 2,
            "total": 2602
        },
        {
            "page": "Silvino Chiappara",
            "pageView": 2,
            "total": 3568
        },
        {
            "page": "Emanuele Toso",
            "pageView": 2,
            "total": 1927
        },
        {
            "page": "Ferruccio Chemello",
            "pageView": 2,
            "total": 1939
        },
        {
            "page": "Franco Nicolini (calciatore)",
            "pageView": 2,
            "total": 3623
        },
        {
            "page": "Giacomo Bozzano",
            "pageView": 2,
            "total": 3700
        },
        {
            "page": "Eugenio Mario Raffo",
            "pageView": 1,
            "total": 1940
        },
        {
            "page": "Giovanni Castagnola",
            "pageView": 1,
            "total": 1575
        },
        {
            "page": "Giovanni Ghio",
            "pageView": 1,
            "total": 1270
        },
        {
            "page": "Angelo Bo",
            "pageView": 0,
            "total": 24
        },
        {
            "page": "Carlo Mendel",
            "pageView": 0,
            "total": 635
        }
    ]
}