{
    "name": "Vazzola",
    "people": [
        {
            "page": "Giorgio Lago",
            "pageView": 4,
            "total": 6086
        },
        {
            "page": "Gina Roma",
            "pageView": 3,
            "total": 5598
        },
        {
            "page": "Flavio Vanzella",
            "pageView": 3,
            "total": 4430
        },
        {
            "page": "Armando Buso",
            "pageView": 2,
            "total": 3080
        },
        {
            "page": "Giovanni Costariol",
            "pageView": 2,
            "total": 2676
        },
        {
            "page": "Giovanni Roma (ciclista)",
            "pageView": 2,
            "total": 1940
        },
        {
            "page": "Luigi Cadorin",
            "pageView": 1,
            "total": 843
        }
    ]
}