{
    "name": "Vercelli",
    "people": [
        {
            "page": "Moise Kean",
            "pageView": 368,
            "total": 1142397
        },
        {
            "page": "Anita Caprioli",
            "pageView": 132,
            "total": 294861
        },
        {
            "page": "Il Sodoma",
            "pageView": 48,
            "total": 74278
        },
        {
            "page": "Fabio Ghidoni",
            "pageView": 38,
            "total": 156110
        },
        {
            "page": "Domenico Marocchino",
            "pageView": 33,
            "total": 67949
        },
        {
            "page": "Virginio Rosetta",
            "pageView": 30,
            "total": 48610
        },
        {
            "page": "Vittorio Ghidella",
            "pageView": 27,
            "total": 45793
        },
        {
            "page": "Linda Sini",
            "pageView": 24,
            "total": 48224
        },
        {
            "page": "Vittorio Mero",
            "pageView": 24,
            "total": 72322
        },
        {
            "page": "Carlo Pellion di Persano",
            "pageView": 22,
            "total": 35243
        },
        {
            "page": "Davide Micillo",
            "pageView": 18,
            "total": 28971
        },
        {
            "page": "Ugo Ferrante",
            "pageView": 18,
            "total": 27891
        },
        {
            "page": "Giuseppe Momo",
            "pageView": 16,
            "total": 25705
        },
        {
            "page": "Alessandro Galante Garrone",
            "pageView": 15,
            "total": 24673
        },
        {
            "page": "Eusebio Castigliano",
            "pageView": 15,
            "total": 32891
        },
        {
            "page": "Pietro Ferraris",
            "pageView": 14,
            "total": 23585
        },
        {
            "page": "Valerio Castronovo",
            "pageView": 13,
            "total": 21631
        },
        {
            "page": "Guglielmo da Vercelli",
            "pageView": 13,
            "total": 24220
        },
        {
            "page": "Giovanni Pellielo",
            "pageView": 12,
            "total": 52789
        },
        {
            "page": "Tomaso Staiti di Cuddia delle Chiuse",
            "pageView": 10,
            "total": 26740
        },
        {
            "page": "Giuseppe Cavanna",
            "pageView": 9,
            "total": 14624
        },
        {
            "page": "Luigi Giuliano (calciatore)",
            "pageView": 9,
            "total": 17746
        },
        {
            "page": "Luigi Galleani",
            "pageView": 9,
            "total": 14510
        },
        {
            "page": "Cristiano Bodo",
            "pageView": 8.5,
            "total": 8672
        },
        {
            "page": "Magica Aidan",
            "pageView": 7,
            "total": 23005
        },
        {
            "page": "Eusebio Bava",
            "pageView": 7,
            "total": 11056
        },
        {
            "page": "Roberto Sambonet",
            "pageView": 7,
            "total": 11516
        },
        {
            "page": "Teobaldo Depetrini",
            "pageView": 7,
            "total": 10406
        },
        {
            "page": "Antonio Ambrogio Alciati",
            "pageView": 7,
            "total": 10818
        },
        {
            "page": "Roberto Sbaratto",
            "pageView": 7,
            "total": 13362
        },
        {
            "page": "Guido Ara",
            "pageView": 7,
            "total": 11119
        },
        {
            "page": "Tommaso Raspino",
            "pageView": 6,
            "total": 11577
        },
        {
            "page": "Giovan Battista Pirovano",
            "pageView": 6,
            "total": 9226
        },
        {
            "page": "Angelo Gilardino",
            "pageView": 6,
            "total": 8935
        },
        {
            "page": "Maurizio Ambrosini",
            "pageView": 6,
            "total": 9601
        },
        {
            "page": "Guala Bicchieri",
            "pageView": 6,
            "total": 15321
        },
        {
            "page": "Cesare Picco",
            "pageView": 5,
            "total": 9725
        },
        {
            "page": "Gabriele Savino",
            "pageView": 5,
            "total": 7297
        },
        {
            "page": "Luciano Angeleri",
            "pageView": 5,
            "total": 7534
        },
        {
            "page": "Carlo Galante Garrone",
            "pageView": 5,
            "total": 8471
        },
        {
            "page": "Giuseppe Berta",
            "pageView": 4,
            "total": 5782
        },
        {
            "page": "Mario Ardissone",
            "pageView": 4,
            "total": 6163
        },
        {
            "page": "Carlo Alberto Quario",
            "pageView": 4,
            "total": 7071
        },
        {
            "page": "Carlot-ta",
            "pageView": 4,
            "total": 7601
        },
        {
            "page": "Roberto Amadè",
            "pageView": 4,
            "total": 8121
        },
        {
            "page": "Gerolamo Giovenone",
            "pageView": 4,
            "total": 6716
        },
        {
            "page": "Urbano Rattazzi iuniore",
            "pageView": 4,
            "total": 7501
        },
        {
            "page": "Laura Bosio",
            "pageView": 4,
            "total": 6483
        },
        {
            "page": "Antonio Bruna",
            "pageView": 3,
            "total": 4023
        },
        {
            "page": "Giulio Libano",
            "pageView": 3,
            "total": 6706
        },
        {
            "page": "Achille Giovanni Cagna",
            "pageView": 3,
            "total": 4605
        },
        {
            "page": "Dario Perucca",
            "pageView": 3,
            "total": 4828
        },
        {
            "page": "Alberto Barberis",
            "pageView": 3,
            "total": 5312
        },
        {
            "page": "Franco Ricciardiello",
            "pageView": 3,
            "total": 4973
        },
        {
            "page": "Antonio Roasio",
            "pageView": 3,
            "total": 4507
        },
        {
            "page": "Giuseppe Garrone",
            "pageView": 3,
            "total": 4959
        },
        {
            "page": "Federica Valeriano",
            "pageView": 3,
            "total": 5405
        },
        {
            "page": "Francesco Antonio Vallotti",
            "pageView": 3,
            "total": 5647
        },
        {
            "page": "Mario Zanello",
            "pageView": 3,
            "total": 4372
        },
        {
            "page": "Carolina Zardo",
            "pageView": 3,
            "total": 5125
        },
        {
            "page": "Alessandro Pellegrini",
            "pageView": 3,
            "total": 5612
        },
        {
            "page": "Giuseppe Cominetti",
            "pageView": 3,
            "total": 5119
        },
        {
            "page": "Carlo Corna",
            "pageView": 3,
            "total": 4236
        },
        {
            "page": "Giuseppe Parodi",
            "pageView": 3,
            "total": 3801
        },
        {
            "page": "Costa (cantante)",
            "pageView": 3,
            "total": 5262
        },
        {
            "page": "Giuseppe Pozzo",
            "pageView": 3,
            "total": 4257
        },
        {
            "page": "Marcello Bertinetti",
            "pageView": 3,
            "total": 5264
        },
        {
            "page": "Giuseppe Failla",
            "pageView": 3,
            "total": 5061
        },
        {
            "page": "Emanuele Pugliese",
            "pageView": 3,
            "total": 5226
        },
        {
            "page": "Mario Ferraris",
            "pageView": 3,
            "total": 5029
        },
        {
            "page": "Edoardo Arborio Mella",
            "pageView": 3,
            "total": 4359
        },
        {
            "page": "Ermes Borsetti",
            "pageView": 3,
            "total": 4764
        },
        {
            "page": "Enrico Allorio",
            "pageView": 3,
            "total": 4435
        },
        {
            "page": "Luigi Bozino",
            "pageView": 3,
            "total": 3990
        },
        {
            "page": "Giorgio Liuzzi",
            "pageView": 3,
            "total": 5464
        },
        {
            "page": "Antonio Garbasso",
            "pageView": 3,
            "total": 5314
        },
        {
            "page": "Eugenio Brunetta d'Usseaux",
            "pageView": 2,
            "total": 3581
        },
        {
            "page": "Mario Marazzani",
            "pageView": 2,
            "total": 3066
        },
        {
            "page": "Pietro Perotti",
            "pageView": 2,
            "total": 2402
        },
        {
            "page": "Franco Bertinetti",
            "pageView": 2,
            "total": 2512
        },
        {
            "page": "Luigi Bajardi",
            "pageView": 2,
            "total": 3483
        },
        {
            "page": "Ermenegildo Bertola",
            "pageView": 2,
            "total": 2262
        },
        {
            "page": "Emilia Bicchieri",
            "pageView": 2,
            "total": 2632
        },
        {
            "page": "Alessandro Roberto",
            "pageView": 2,
            "total": 3588
        },
        {
            "page": "Natale Balossino",
            "pageView": 2,
            "total": 3470
        },
        {
            "page": "Carlo Boggio",
            "pageView": 2,
            "total": 2744
        },
        {
            "page": "Francesco Borello",
            "pageView": 2,
            "total": 3188
        },
        {
            "page": "Mario Maratelli",
            "pageView": 2,
            "total": 3305
        },
        {
            "page": "Dante Amarilli",
            "pageView": 2,
            "total": 2278
        },
        {
            "page": "Paolo Barbero",
            "pageView": 2,
            "total": 1776
        },
        {
            "page": "Nino Malinverni",
            "pageView": 2,
            "total": 2001
        },
        {
            "page": "Ermando Malinverni",
            "pageView": 2,
            "total": 2552
        },
        {
            "page": "Louis Boulanger",
            "pageView": 2,
            "total": 2851
        },
        {
            "page": "Niccolò Barbieri",
            "pageView": 2,
            "total": 3906
        },
        {
            "page": "Severino Rosso",
            "pageView": 2,
            "total": 2881
        },
        {
            "page": "Marco Barnabino",
            "pageView": 2,
            "total": 2395
        },
        {
            "page": "Giovanni Palma",
            "pageView": 2,
            "total": 2278
        },
        {
            "page": "Giovanni Brutto",
            "pageView": 2,
            "total": 3506
        },
        {
            "page": "Carlo Luigi Buronzo del Signore",
            "pageView": 2,
            "total": 3538
        },
        {
            "page": "Antonio Labacco",
            "pageView": 2,
            "total": 3088
        },
        {
            "page": "Giovanni Agostino Perotti",
            "pageView": 2,
            "total": 2158
        },
        {
            "page": "Emiliano Avogadro della Motta",
            "pageView": 2,
            "total": 2466
        },
        {
            "page": "Egidio Scansetti",
            "pageView": 2,
            "total": 2027
        },
        {
            "page": "Luigi Caligaris (calciatore)",
            "pageView": 2,
            "total": 2170
        },
        {
            "page": "Valeriano Ottino",
            "pageView": 2,
            "total": 3418
        },
        {
            "page": "Alice Greppi",
            "pageView": 2,
            "total": 1289
        },
        {
            "page": "Walter Carasso",
            "pageView": 2,
            "total": 2008
        },
        {
            "page": "Laura Schrader",
            "pageView": 2,
            "total": 2106
        },
        {
            "page": "Luigi Casalino",
            "pageView": 2,
            "total": 2757
        },
        {
            "page": "Giuseppe Seccatore",
            "pageView": 2,
            "total": 1780
        },
        {
            "page": "Giuseppe Servetto",
            "pageView": 2,
            "total": 2264
        },
        {
            "page": "Remigio Bellini",
            "pageView": 2,
            "total": 2173
        },
        {
            "page": "Pietro Povero",
            "pageView": 2,
            "total": 2447
        },
        {
            "page": "Manuele Cecconello",
            "pageView": 2,
            "total": 2767
        },
        {
            "page": "Piero Pozzi",
            "pageView": 2,
            "total": 2915
        },
        {
            "page": "Sara Cristina Cometti",
            "pageView": 2,
            "total": 2888
        },
        {
            "page": "Alessandro Avogadro di Casanova",
            "pageView": 2,
            "total": 2994
        },
        {
            "page": "Daniele Statella",
            "pageView": 2,
            "total": 3594
        },
        {
            "page": "Sergio Pensotti",
            "pageView": 2,
            "total": 3240
        },
        {
            "page": "Carlo Giovanni Testori",
            "pageView": 2,
            "total": 1891
        },
        {
            "page": "Giuseppe Tosi (calciatore)",
            "pageView": 2,
            "total": 2241
        },
        {
            "page": "Mario Curti",
            "pageView": 2,
            "total": 2536
        },
        {
            "page": "Luciano Degara",
            "pageView": 2,
            "total": 2467
        },
        {
            "page": "Franco Tricerri",
            "pageView": 2,
            "total": 1256
        },
        {
            "page": "Elisa Uga",
            "pageView": 2,
            "total": 3031
        },
        {
            "page": "Angelo Piccaluga",
            "pageView": 2,
            "total": 3502
        },
        {
            "page": "Amedeo Peyron (architetto)",
            "pageView": 2,
            "total": 2157
        },
        {
            "page": "Vittorio Varese",
            "pageView": 2,
            "total": 2119
        },
        {
            "page": "Carlo Verga",
            "pageView": 2,
            "total": 1813
        },
        {
            "page": "Sergio Ferraris",
            "pageView": 2,
            "total": 2332
        },
        {
            "page": "Angelo Agostini",
            "pageView": 2,
            "total": 3091
        },
        {
            "page": "Gustavo Gay",
            "pageView": 2,
            "total": 2457
        },
        {
            "page": "Vincenzo Fresia",
            "pageView": 2,
            "total": 2536
        },
        {
            "page": "Giovanni Antonio Ranza",
            "pageView": 2,
            "total": 3237
        },
        {
            "page": "Diego Baiardi",
            "pageView": 2,
            "total": 2407
        },
        {
            "page": "Virginia Galante Garrone",
            "pageView": 2,
            "total": 3700
        },
        {
            "page": "Feliciano Gattinara di Gattinara",
            "pageView": 2,
            "total": 2070
        },
        {
            "page": "Renzo Masoero",
            "pageView": 2,
            "total": 2512
        },
        {
            "page": "Ennio Baiardi",
            "pageView": 2,
            "total": 1894
        },
        {
            "page": "Eugenio Garrone",
            "pageView": 2,
            "total": 4042
        },
        {
            "page": "Francesco Bergamasco",
            "pageView": 2,
            "total": 2452
        },
        {
            "page": "Alfredo Gatti",
            "pageView": 2,
            "total": 2935
        },
        {
            "page": "Massimo Struffi",
            "pageView": 1,
            "total": 1660
        },
        {
            "page": "Aldo Pondrano",
            "pageView": 1,
            "total": 1424
        },
        {
            "page": "Franco Fontana (calciatore 1938)",
            "pageView": 1,
            "total": 1725
        },
        {
            "page": "Renzo Genta",
            "pageView": 1,
            "total": 1518
        },
        {
            "page": "Vittorio Florio",
            "pageView": 1,
            "total": 1109
        },
        {
            "page": "Giovanni Stefano Aiazza",
            "pageView": 1,
            "total": 1251
        },
        {
            "page": "Luigi Andreoni",
            "pageView": 1,
            "total": 1565
        },
        {
            "page": "Gian Maria Cominetti",
            "pageView": 1,
            "total": 1483
        },
        {
            "page": "Paolo Giuseppe Avogadro di Casanova",
            "pageView": 1,
            "total": 731
        },
        {
            "page": "Uguccione Caqualoro",
            "pageView": 1,
            "total": 1421
        },
        {
            "page": "Carlo Guala",
            "pageView": 1,
            "total": 1022
        },
        {
            "page": "Luigi Guala",
            "pageView": 1,
            "total": 1137
        },
        {
            "page": "Giovan Battista Calandra",
            "pageView": 1,
            "total": 1171
        },
        {
            "page": "Barnaba Cagnoli",
            "pageView": 1,
            "total": 868
        },
        {
            "page": "Bernardino Peyron",
            "pageView": 1,
            "total": 1024
        },
        {
            "page": "Germano Lanino",
            "pageView": 1,
            "total": 1513
        },
        {
            "page": "Giuseppe Agù",
            "pageView": 1,
            "total": 1753
        },
        {
            "page": "Angelo Bredo",
            "pageView": 1,
            "total": 1211
        },
        {
            "page": "Giovanni Bottino Barzizza",
            "pageView": 1,
            "total": 1532
        },
        {
            "page": "Archimede Bottazzi",
            "pageView": 1,
            "total": 1581
        },
        {
            "page": "Uguccio Borromeo",
            "pageView": 1,
            "total": 1365
        },
        {
            "page": "Ettore Berra",
            "pageView": 1,
            "total": 1236
        },
        {
            "page": "Eugenio Bergamasco",
            "pageView": 1,
            "total": 1613
        },
        {
            "page": "Aldo Beretta",
            "pageView": 1,
            "total": 1464
        },
        {
            "page": "Angelo Beltaro",
            "pageView": 1,
            "total": 1371
        },
        {
            "page": "Felice Avogadro di Quinto",
            "pageView": 1,
            "total": 1670
        },
        {
            "page": "Guido Minghetti",
            "pageView": 1,
            "total": 1183
        },
        {
            "page": "Alfredo Bajardi",
            "pageView": 1,
            "total": 1797
        },
        {
            "page": "Renzo Monti",
            "pageView": 1,
            "total": 1678
        },
        {
            "page": "Franco Baucè",
            "pageView": 1,
            "total": 1835
        },
        {
            "page": "Gaudenzio Nazario",
            "pageView": 1,
            "total": 1157
        },
        {
            "page": "Antonio Nicolazzini",
            "pageView": 1,
            "total": 1407
        },
        {
            "page": "Davide Schaier",
            "pageView": 1,
            "total": 1146
        },
        {
            "page": "Giovanni Pallavicini",
            "pageView": 1,
            "total": 1701
        },
        {
            "page": "Ferdinando Santagostino",
            "pageView": 1,
            "total": 1553
        },
        {
            "page": "Carlo Rosaspina",
            "pageView": 1,
            "total": 1832
        },
        {
            "page": "Federico Roncarolo",
            "pageView": 1,
            "total": 1234
        },
        {
            "page": "Piero Romagnolo",
            "pageView": 1,
            "total": 1113
        },
        {
            "page": "Evasio Radice",
            "pageView": 1,
            "total": 1516
        },
        {
            "page": "Gino Pensotti",
            "pageView": 1,
            "total": 1316
        },
        {
            "page": "Giovanni Pramaggiore",
            "pageView": 1,
            "total": 1241
        },
        {
            "page": "Giuseppe Peretta",
            "pageView": 1,
            "total": 1371
        },
        {
            "page": "Davide Motaran",
            "pageView": 0,
            "total": 385
        },
        {
            "page": "Luigi Sessa (arbitro)",
            "pageView": 0,
            "total": 739
        },
        {
            "page": "Gabriele Bagnasco",
            "pageView": 0,
            "total": 701
        },
        {
            "page": "Carlo Gallardi",
            "pageView": 0,
            "total": 95
        },
        {
            "page": "Enzo Busca",
            "pageView": 0,
            "total": 764
        },
        {
            "page": "Piero Ciocchetti",
            "pageView": 0,
            "total": 233
        },
        {
            "page": "Andrea Corsaro",
            "pageView": 0,
            "total": 2144
        },
        {
            "page": "Valerio Donnianni",
            "pageView": 0,
            "total": 49
        },
        {
            "page": "Giovanni Gastaldi",
            "pageView": 0,
            "total": 518
        }
    ]
}